[{"id": "CA_27577334", "address": "2600 Del Amo Boulevard, Torrance, CA, 90503", "city": "Torrance", "state": "CA", "type": "Office", "vertical": "Commercial", "sqft": 86000.0, "opex": 85794.59926, "valuation": 1143927.9901333335, "carbon": 29.29454781, "eui": 46.83583866, "image": "CA_27577334_streetview.jpg", "lat": 33.8468301, "lon": -118.3332896}, {"id": "CA_27572367", "address": "3003 East Colorado Boulevard, Pasadena, CA, 91107", "city": "Pasadena", "state": "CA", "type": "Office", "vertical": "Commercial", "sqft": 61144.0, "opex": 39662.04093, "valuation": 528827.2124000001, "carbon": 14.06316424, "eui": 36.8348101, "image": "CA_27572367_Mapquest.jpg", "lat": 34.1473721, "lon": -118.0877603}, {"id": "CA_27577353", "address": "150 West Blaine Street, Corona, CA, 92880", "city": "Corona", "state": "CA", "type": "Office", "vertical": "Commercial", "sqft": 65306.0, "opex": 24672.92947, "valuation": 328972.39293333335, "carbon": 6.967309229, "eui": 28.17701098, "image": "CA_27577353_Ganahllumbercorona.jpg", "lat": 33.8835149, "lon": -117.567483}]