[{"id": "CA_64621892", "address": "74-910 Aztec Road, Palm Desert, CA, 92260", "city": "Palm Desert", "state": "CA", "type": "PreK-12", "vertical": "Education", "sqft": 261323.0, "opex": 159305.2132, "valuation": 0.0, "carbon": 98.29777657, "eui": 51.53882628, "image": "CA_64621892_Serpapi.jpg", "lat": 33.7310859, "lon": -116.3583936}, {"id": "CA_36340622", "address": "79-255 Blackhawk Way, La Quinta, CA, 92253", "city": "La Quinta", "state": "CA", "type": "PreK-12", "vertical": "Education", "sqft": 291270.0, "opex": 133525.57, "valuation": 0.0, "carbon": 82.39069135, "eui": 42.0956242, "image": "CA_36340622_Laquintahighschoolde.jpg", "lat": 33.7145578, "lon": -116.2819946}, {"id": "CA_36327607", "address": "39-800 Liberty Dr., Palm Desert, CA, 92211", "city": "Palm Desert", "state": "CA", "type": "PreK-12", "vertical": "Education", "sqft": 70044.0, "opex": 84345.79016, "valuation": 0.0, "carbon": 56.71246549, "eui": 98.90233705, "image": "CA_36327607_Serpapi.jpg", "lat": 33.7592417, "lon": -116.3153958}, {"id": "CA_6877783", "address": "69250 Dinah Shore Drive, Cathedral City, CA, 92234", "city": "Cathedral City", "state": "CA", "type": "PreK-12", "vertical": "Education", "sqft": 243031.0, "opex": 65023.97567, "valuation": 0.0, "carbon": 132.0916396, "eui": 49.50300373, "image": "CA_6877783_Cathedralcityhighsch.jpg", "lat": 33.8040016, "lon": -116.4506472}, {"id": "CA_6877966", "address": "31001 Rattler Road, Rancho Mirage, CA, 92270", "city": "Rancho Mirage", "state": "CA", "type": "PreK-12", "vertical": "Education", "sqft": 331390.0, "opex": 62195.22418, "valuation": 0.0, "carbon": 84.36557206, "eui": 35.68878542, "image": "CA_6877966_places.jpg", "lat": 33.8224701, "lon": -116.4348803}, {"id": "CA_36299560", "address": "44-210 Warner Trail, Indian Wells, CA, 92210", "city": "Indian Wells", "state": "CA", "type": "PreK-12", "vertical": "Education", "sqft": 53917.0, "opex": 45898.08325, "valuation": 0.0, "carbon": 30.86097666, "eui": 69.28350537, "image": "CA_36299560_streetview.jpg", "lat": 33.727937, "lon": -116.3119824}, {"id": "CA_6877879", "address": "2401 East Baristo Road, Palm Springs, CA, 92262", "city": "Palm Springs", "state": "CA", "type": "PreK-12", "vertical": "Education", "sqft": 291646.0, "opex": 45025.18562, "valuation": 0.0, "carbon": 60.60244665, "eui": 25.78340694, "image": "CA_6877879_Homes.jpg", "lat": 33.8180316, "lon": -116.5212164}, {"id": "CA_6877867", "address": "65850 Pierson Boulevard, Desert Hot Springs, CA, 92240", "city": "Desert Hot Springs", "state": "CA", "type": "PreK-12", "vertical": "Education", "sqft": 219087.0, "opex": 29984.86127, "valuation": 0.0, "carbon": 14.85128109, "eui": 23.09677799, "image": "CA_6877867_Homes.jpg", "lat": 33.9645127, "lon": -116.5175864}, {"id": "CA_36340178", "address": "79-767 Ave. 39, Indio, CA, 92203", "city": "Indio", "state": "CA", "type": "PreK-12", "vertical": "Education", "sqft": 108948.0, "opex": 26654.59485, "valuation": 0.0, "carbon": 13.20182464, "eui": 31.28313633, "image": "", "lat": 33.7645054, "lon": -116.2740166}, {"id": "CA_36340174", "address": "78-900 Ave. 50, La Quinta, CA, 92253", "city": "La Quinta", "state": "CA", "type": "PreK-12", "vertical": "Education", "sqft": 70543.0, "opex": 25264.81695, "valuation": 0.0, "carbon": 14.75052421, "eui": 37.09929848, "image": "CA_36340174_Schoolmessenger.jpg", "lat": 33.6875446, "lon": -116.2870723}, {"id": "CA_6877950", "address": "34606 Plumley Road, Cathedral City, CA, 92234", "city": "Cathedral City", "state": "CA", "type": "PreK-12", "vertical": "Education", "sqft": 107368.0, "opex": 24194.60037, "valuation": 0.0, "carbon": 13.3223357, "eui": 36.71402559, "image": "CA_6877950_Palmspringsunifiedsc.jpg", "lat": 33.7990498, "lon": -116.4490956}, {"id": "CA_60951092", "address": "43495 Palm Royale Dr, La Quinta, CA, 92211", "city": "La Quinta", "state": "CA", "type": "PreK-12", "vertical": "Education", "sqft": 115886.0, "opex": 23678.7737, "valuation": 0.0, "carbon": 11.72792233, "eui": 26.12676857, "image": "CA_60951092_Yelp.jpg", "lat": 33.7324609, "lon": -116.3013177}, {"id": "CA_6877930", "address": "69300 30Th Avenue, Cathedral City, CA, 92234", "city": "Cathedral City", "state": "CA", "type": "PreK-12", "vertical": "Education", "sqft": 118522.0, "opex": 22774.57095, "valuation": 0.0, "carbon": 30.94889945, "eui": 33.3701566, "image": "CA_6877930_Homes.jpg", "lat": 33.8318005, "lon": -116.4524912}, {"id": "CA_6877960", "address": "1011 East Vista Chino, Palm Springs, CA, 92262", "city": "Palm Springs", "state": "CA", "type": "PreK-12", "vertical": "Education", "sqft": 139546.0, "opex": 20898.89814, "valuation": 0.0, "carbon": 25.83709744, "eui": 25.68276411, "image": "CA_6877960_Homes.jpg", "lat": 33.8442057, "lon": -116.5358357}, {"id": "CA_6877977", "address": "30800 San Luis Rey Drive, Cathedral City, CA, 92234", "city": "Cathedral City", "state": "CA", "type": "PreK-12", "vertical": "Education", "sqft": 67500.0, "opex": 20840.35764, "valuation": 0.0, "carbon": 23.57941328, "eui": 39.74405197, "image": "CA_6877977_Palmspringsunifiedsc.jpg", "lat": 33.8255656, "lon": -116.489161}, {"id": "CA_6877979", "address": "31495 Robert Road, Thousand Palms, CA, 92276", "city": "Thousand Palms", "state": "CA", "type": "PreK-12", "vertical": "Education", "sqft": 65609.0, "opex": 19214.56106, "valuation": 0.0, "carbon": 22.21306093, "eui": 38.30133924, "image": "CA_6877979_places.jpg", "lat": 33.8208674, "lon": -116.3977179}, {"id": "CA_6877956", "address": "9250 Sonora Drive, Desert Hot Springs, CA, 92240", "city": "Desert Hot Springs", "state": "CA", "type": "PreK-12", "vertical": "Education", "sqft": 148093.0, "opex": 19208.19382, "valuation": 0.0, "carbon": 8.875888616, "eui": 23.46143234, "image": "CA_6877956_Palmspringsunifiedsc.jpg", "lat": 33.9813112, "lon": -116.5174373}, {"id": "CA_6877940", "address": "30310 Landau Boulevard, Cathedral City, CA, 92234", "city": "Cathedral City", "state": "CA", "type": "PreK-12", "vertical": "Education", "sqft": 66641.0, "opex": 16203.5998, "valuation": 0.0, "carbon": 9.818936844, "eui": 35.39536772, "image": "CA_6877940_Www.jpg", "lat": 33.8296311, "lon": -116.4738462}, {"id": "CA_6877926", "address": "68750 Hacienda Avenue, Desert Hot Springs, CA, 92240", "city": "Desert Hot Springs", "state": "CA", "type": "PreK-12", "vertical": "Education", "sqft": 69053.0, "opex": 15300.59722, "valuation": 0.0, "carbon": 16.6335, "eui": 33.21665369, "image": "CA_6877926_Palmspringsunifiedsc.jpg", "lat": 33.9505147, "lon": -116.4608237}, {"id": "CA_36327628", "address": "78-870 Ave. 50, La Quinta, CA, 92253", "city": "La Quinta", "state": "CA", "type": "PreK-12", "vertical": "Education", "sqft": 67029.0, "opex": 14752.55514, "valuation": 0.0, "carbon": 7.633394298, "eui": 28.25848554, "image": "CA_36327628_Serpapi.jpg", "lat": 33.6859615, "lon": -116.2881334}, {"id": "CA_6877913", "address": "66755 Two Bunch Palms Trail, Desert Hot Springs, CA, 92240", "city": "Desert Hot Springs", "state": "CA", "type": "PreK-12", "vertical": "Education", "sqft": 115997.0, "opex": 14472.49808, "valuation": 0.0, "carbon": 7.16812178, "eui": 21.05536178, "image": "CA_6877913_Thedesertsun.jpg", "lat": 33.945008, "lon": -116.4969483}, {"id": "CA_6877726", "address": "69300 Converse Road, Cathedral City, CA, 92234", "city": "Cathedral City", "state": "CA", "type": "PreK-12", "vertical": "Education", "sqft": 90675.0, "opex": 11782.43173, "valuation": 0.0, "carbon": 12.95335123, "eui": 22.7198445, "image": "CA_6877726_Palmspringsunifiedsc.jpg", "lat": 33.7907365, "lon": -116.4546695}, {"id": "CA_36321417", "address": "41-633 Gore St., Indio, CA, 92203", "city": "Indio", "state": "CA", "type": "PreK-12", "vertical": "Education", "sqft": 56000.0, "opex": 11693.52136, "valuation": 0.0, "carbon": 5.403443662, "eui": 28.61879279, "image": "", "lat": 33.7467733, "lon": -116.2266779}, {"id": "CA_6877975", "address": "14250 West Drive, Desert Hot Springs, CA, 92240", "city": "Desert Hot Springs", "state": "CA", "type": "PreK-12", "vertical": "Education", "sqft": 78442.0, "opex": 11447.87688, "valuation": 0.0, "carbon": 5.670049157, "eui": 24.62874353, "image": "CA_6877975_Homes.jpg", "lat": 33.9454933, "lon": -116.5084962}, {"id": "CA_6877971", "address": "69310 Mccallum Way, Cathedral City, CA, 92234", "city": "Cathedral City", "state": "CA", "type": "PreK-12", "vertical": "Education", "sqft": 75410.0, "opex": 11335.28996, "valuation": 0.0, "carbon": 5.865203484, "eui": 24.28181143, "image": "CA_6877971_Palmspringsunifiedsc.jpg", "lat": 33.8241965, "lon": -116.4536437}, {"id": "CA_6877921", "address": "11605 West Dr, Desert Hot Springs, CA, 92240", "city": "Desert Hot Springs", "state": "CA", "type": "PreK-12", "vertical": "Education", "sqft": 56104.0, "opex": 9945.591022, "valuation": 0.0, "carbon": 10.9524344, "eui": 27.53974408, "image": "CA_6877921_Palmspringsunifiedsc.jpg", "lat": 33.9645924, "lon": -116.5110703}, {"id": "CA_6877406", "address": "67501 Camino Campanero, Desert Hot Springs, CA, 92240", "city": "Desert Hot Springs", "state": "CA", "type": "PreK-12", "vertical": "Education", "sqft": 67187.0, "opex": 9773.861641, "valuation": 0.0, "carbon": 4.840921734, "eui": 24.54974028, "image": "CA_6877406_Homes.jpg", "lat": 33.9389327, "lon": -116.4849204}, {"id": "CA_6877470", "address": "67067 Desert View Avenue, Desert Hot Springs, CA, 92240", "city": "Desert Hot Springs", "state": "CA", "type": "PreK-12", "vertical": "Education", "sqft": 66087.0, "opex": 9248.500541, "valuation": 0.0, "carbon": 11.9930655, "eui": 24.47093982, "image": "CA_6877470_Palmspringsunifiedsc.jpg", "lat": 33.956851, "lon": -116.489864}, {"id": "CA_6877934", "address": "777 East Tachevah Drive, Palm Springs, CA, 92262", "city": "Palm Springs", "state": "CA", "type": "PreK-12", "vertical": "Education", "sqft": 66711.0, "opex": 8347.372863, "valuation": 0.0, "carbon": 3.949615029, "eui": 22.10422269, "image": "CA_6877934_Palmspringsunifiedsc.jpg", "lat": 33.8374563, "lon": -116.5380166}, {"id": "CA_6877049", "address": "65750 Avenida Jalisco, Desert Hot Springs, CA, 92240", "city": "Desert Hot Springs", "state": "CA", "type": "PreK-12", "vertical": "Education", "sqft": 87136.0, "opex": 7551.414908, "valuation": 0.0, "carbon": 3.155107226, "eui": 17.33695258, "image": "CA_6877049_Palmspringsunifiedsc.jpg", "lat": 33.9809403, "lon": -116.5146771}, {"id": "CA_6877969", "address": "67-700 Verona Road, Cathedral City, CA, 92234", "city": "Cathedral City", "state": "CA", "type": "PreK-12", "vertical": "Education", "sqft": 75849.0, "opex": 7186.255106, "valuation": 0.0, "carbon": 3.241149607, "eui": 17.5583686, "image": "CA_6877969_Homes.jpg", "lat": 33.8530482, "lon": -116.4809794}]