[{"id": "DC_5494061", "address": "1200 18th St NW, Washington, DC 20036", "city": "Washington", "state": "DC", "type": "Office", "vertical": "Commercial", "sqft": 192584.0, "opex": 1154763.376, "valuation": 16496619.657142855, "carbon": 113.6019472, "eui": 75.58028595, "image": "DC_5494061_streetview.jpg", "lat": 38.90598826, "lon": -77.04210182}, {"id": "CAM_1732", "address": "625 Mt Auburn St, Watertown, MA 02472", "city": "Watertown", "state": "MA", "type": "Office", "vertical": "Commercial", "sqft": 137421.0, "opex": 286307.7873, "valuation": 4090111.247142857, "carbon": 208.8375391, "eui": 85.17009846, "image": "CAM_1732_streetview.jpg", "lat": 42.3756, "lon": -71.1471}, {"id": "DC_5488342", "address": "1208 18th St NW, Washington, DC 20036", "city": "Washington", "state": "DC", "type": "Office", "vertical": "Commercial", "sqft": 190994.0, "opex": 103090.5416, "valuation": 1472722.0228571426, "carbon": 38.19622631, "eui": 38.68393632, "image": "DC_5488342_streetview.jpg", "lat": 38.90604542, "lon": -77.04191534}, {"id": "BOS_106068", "address": "1234 Soldiers Field Rd, Boston, MA, 02134", "city": "Boston", "state": "MA", "type": "Hotel", "vertical": "Commercial", "sqft": 61656.0, "opex": 10960.61623, "valuation": 146141.54973333335, "carbon": 2.532381653, "eui": 31.73176333, "image": "BOS_106068_streetview.jpg", "lat": 42.3640327, "lon": -71.1364009}]