[{"id": "SJ_160", "address": "3 W Plumeria Dr, San Jose, CA, 95134", "city": "San Jose", "state": "CA", "type": "Office", "vertical": "Commercial", "sqft": 79341.0, "opex": 238746.1041, "valuation": 3183281.3880000003, "carbon": 385.4851039, "eui": 192.6025769, "image": "SJ_160_GooglePlaces.jpg", "lat": 37.3912092, "lon": -121.9339079}, {"id": "CA_15668543", "address": "75 W. Plumeria, San Jose, CA, 95134", "city": "San Jose", "state": "CA", "type": "Office", "vertical": "Commercial", "sqft": 62500.0, "opex": 43129.75208, "valuation": 575063.3610666667, "carbon": 10.97924661, "eui": 32.51354829, "image": "CA_15668543_streetview.jpg", "lat": 37.390586, "lon": -121.9347399}, {"id": "SJ_158", "address": "2820 Orchard Pkwy, San Jose, CA, 95134", "city": "San Jose", "state": "CA", "type": "Office", "vertical": "Commercial", "sqft": 62260.0, "opex": 40815.91102, "valuation": 544212.1469333334, "carbon": 45.37568195, "eui": 60.31610785, "image": "SJ_158_Themercurynews.jpg", "lat": 37.3905195, "lon": -121.9344083}]