[{"id": "CA_3593089", "address": "4215 Sorrento Valley Boulevard, San Diego, CA, 92121", "city": "San Diego", "state": "CA", "type": "Medical Office/Lab", "vertical": "Healthcare", "sqft": 56053.0, "opex": 25294.27529, "valuation": 0.0, "carbon": 27.16261313, "eui": 229.5501108, "image": "CA_3593089_Loopnet.jpg", "lat": 32.9043459, "lon": -117.2142376}, {"id": "CA_3371609", "address": "9535 Waples Street, San Diego, CA, 92121", "city": "San Diego", "state": "CA", "type": "Medical Office/Lab", "vertical": "Healthcare", "sqft": 50055.0, "opex": 13195.46204, "valuation": 0.0, "carbon": 15.15102826, "eui": 161.0114624, "image": "CA_3371609_streetview.jpg", "lat": 32.902628, "lon": -117.1826291}, {"id": "CA_3593055", "address": "6122 Nancy Ridge Drive, San Diego, CA, 92121", "city": "San Diego", "state": "CA", "type": "Medical Office/Lab", "vertical": "Healthcare", "sqft": 68000.0, "opex": 1946.926658, "valuation": 0.0, "carbon": 3.346938587, "eui": 28.49812244, "image": "CA_3593055_streetview.jpg", "lat": 32.8891057, "lon": -117.1871777}]