[{"id": "NYC_1008260011", "address": "49 West 24Th Street, New York, NY, 10010", "city": "New York", "state": "NY", "type": "Office", "vertical": "Commercial", "sqft": 41800.0, "opex": 35289.17937, "valuation": 504131.1338571427, "carbon": 87.03296086, "eui": 116.9976794, "image": "NYC_1008260011_Serpapi.jpg", "lat": 40.742946, "lon": -73.990834}, {"id": "NYC_1008260013", "address": "43 West 24Th Street, New York, NY, 10010", "city": "New York", "state": "NY", "type": "Office", "vertical": "Commercial", "sqft": 66214.0, "opex": 32277.4293, "valuation": 461106.1328571428, "carbon": 52.81426753, "eui": 62.97258133, "image": "NYC_1008260013_cyclomedia.jpg", "lat": 40.742883, "lon": -73.990686}, {"id": "NYC_1008250009", "address": "61 West 23Rd Street, New York, NY, 10010", "city": "New York", "state": "NY", "type": "Office", "vertical": "Commercial", "sqft": 46900.0, "opex": 19455.74369, "valuation": 277939.1955714285, "carbon": 20.36578782, "eui": 45.28850746, "image": "NYC_1008250009_cyclomedia.jpg", "lat": 40.742345, "lon": -73.991436}]